pharmaceutisch_weekblad_downloader/__init__.py
pharmaceutisch_weekblad_downloader/pharmaceutisch_weekblad_downloader.py
pharmaceutisch_weekblad_downloader-0.1.2.dist-info/LICENSE
pharmaceutisch_weekblad_downloader-0.1.2.dist-info/METADATA
pharmaceutisch_weekblad_downloader-0.1.2.dist-info/WHEEL
pharmaceutisch_weekblad_downloader-0.1.2.dist-info/entry_points.txt
pharmaceutisch_weekblad_downloader-0.1.2.dist-info/top_level.txt
pharmaceutisch_weekblad_downloader-0.1.2.dist-info/RECORD
