Metadata-Version: 2.1
Name: pharmaceutisch-weekblad-downloader
Version: 0.1.2
Summary: Download Pharmaceutisch Weekblad in PDF format
Home-page: https://gitlab.com/fvdbeek/pharmaceutisch-weekblad-downloader
Author: Folkert van der Beek
Author-email: folkertvanderbeek@gmail.com
License: MIT License
Project-URL: Bug Tracker, https://gitlab.com/fvdbeek/pharmaceutisch-weekblad-downloader/-/issues
Keywords: Pharmaceutisch Weekblad,download,pdf
Classifier: Development Status :: 3 - Alpha
Classifier: License :: OSI Approved :: MIT License
Classifier: Operating System :: OS Independent
Classifier: Programming Language :: Python :: 3
Classifier: Programming Language :: Python :: 3.8
Classifier: Programming Language :: Python :: 3.9
Classifier: Topic :: Utilities
Requires-Python: >=3.8
License-File: LICENSE
Requires-Dist: appdirs
Requires-Dist: beautifulsoup4
Requires-Dist: lxml
Requires-Dist: requests
Requires-Dist: sanitize-filename
Requires-Dist: tabulate
